{
  "1626903355303": {
    "address": "https://helpfulengineering.org/",
    "seconds": 2
  },
  "1626903991044": {
    "address": "https://helpfulengineering.org/",
    "seconds": 1
  },
  "1626904597311": {
    "address": "https://helpfulengineering.org/",
    "seconds": 1
  },
  "1626905703986": {
    "address": "https://helpfulengineering.org/",
    "seconds": 1
  },
  "1626912347124": {
    "address": "https://helpfulengineering.org/",
    "seconds": 2
  },
  "1626914082455": {
    "address": "https://helpfulengineering.org/",
    "seconds": 1
  },
  "1626914581958": {
    "address": "https://helpfulengineering.org/",
    "seconds": 2
  },
  "1626915211405": {
    "address": "https://helpfulengineering.org/",
    "seconds": 2
  },
  "1626915332172": {
    "address": "https://helpfulengineering.org/",
    "seconds": 2
  },
  "1626915724808": {
    "address": "https://helpfulengineering.org/",
    "seconds": 2
  },
  "1626916042584": {
    "address": "https://helpfulengineering.org/",
    "seconds": 1
  },
  "1626916764494": {
    "address": "https://helpfulengineering.org/",
    "seconds": 1
  },
  "1626921027135": {
    "address": "https://helpfulengineering.org/",
    "seconds": 1
  },
  "1626998476621": {
    "address": "https://helpfulengineering.org/",
    "seconds": 1
  },
  "1627084885972": {
    "address": "https://helpfulengineering.org/",
    "seconds": 2
  },
  "1627257840840": {
    "address": "https://helpfulengineering.org/",
    "seconds": 1
  },
  "1627862650181": {
    "address": "https://helpfulengineering.org/",
    "seconds": 2
  },
  "1628467484013": {
    "address": "https://helpfulengineering.org/",
    "seconds": 2
  },
  "1629072293914": {
    "address": "https://helpfulengineering.org/",
    "seconds": 5
  },
  "1629677116871": {
    "address": "https://helpfulengineering.org/",
    "seconds": 5
  },
  "1630281890987": {
    "address": "https://helpfulengineering.org/",
    "seconds": 5
  },
  "1630886699564": {
    "address": "https://helpfulengineering.org/",
    "seconds": 5
  },
  "1631491504648": {
    "address": "https://helpfulengineering.org/",
    "seconds": 5
  },
  "1632096314729": {
    "address": "https://helpfulengineering.org/",
    "seconds": 6
  },
  "1632701099707": {
    "address": "https://helpfulengineering.org/",
    "seconds": 5
  },
  "1635120317005": {
    "address": "https://helpfulengineering.org/",
    "seconds": 5
  },
  "1635725143969": {
    "address": "https://helpfulengineering.org/",
    "seconds": 5
  },
  "1636329897004": {
    "address": "https://helpfulengineering.org/",
    "seconds": 6
  },
  "1636934783093": {
    "address": "https://helpfulengineering.org/",
    "seconds": 5
  },
  "1637539529689": {
    "address": "https://helpfulengineering.org/",
    "seconds": 6
  },
  "1638749170177": {
    "address": "https://helpfulengineering.org/",
    "seconds": 5
  },
  "1639353918825": {
    "address": "https://helpfulengineering.org/",
    "seconds": 4
  },
  "1639958746817": {
    "address": "https://helpfulengineering.org/",
    "seconds": 5
  },
  "1640563552234": {
    "address": "https://helpfulengineering.org/",
    "seconds": 5
  },
  "1641168349795": {
    "address": "https://helpfulengineering.org/",
    "seconds": 5
  },
  "1641773142737": {
    "address": "https://helpfulengineering.org/",
    "seconds": 5
  },
  "1642377960825": {
    "address": "https://helpfulengineering.org/",
    "seconds": 5
  },
  "1642982751558": {
    "address": "https://helpfulengineering.org/",
    "seconds": 5
  },
  "1643587533890": {
    "address": "https://helpfulengineering.org/",
    "seconds": 5
  },
  "1644192452290": {
    "address": "https://helpfulengineering.org/",
    "seconds": 5
  },
  "1644797136196": {
    "address": "https://helpfulengineering.org/",
    "seconds": 5
  },
  "1645402014295": {
    "address": "https://helpfulengineering.org/",
    "seconds": 5
  },
  "1646007490308": {
    "address": "https://helpfulengineering.org/",
    "seconds": 5
  },
  "1646612189574": {
    "address": "https://helpfulengineering.org/",
    "seconds": 5
  },
  "1647821826381": {
    "address": "https://helpfulengineering.org/",
    "seconds": 6
  },
  "1648426675100": {
    "address": "https://helpfulengineering.org/",
    "seconds": 5
  },
  "1649031458351": {
    "address": "https://helpfulengineering.org/",
    "seconds": 6
  },
  "1649636295514": {
    "address": "https://helpfulengineering.org/",
    "seconds": 5
  },
  "1650241321211": {
    "address": "https://helpfulengineering.org/",
    "seconds": 5
  },
  "1650603053541": {
    "address": "https://helpfulengineering.org/",
    "seconds": 4
  },
  "1650845833181": {
    "address": "https://helpfulengineering.org/",
    "seconds": 4
  },
  "1651450759810": {
    "address": "https://helpfulengineering.org/",
    "seconds": 5
  },
  "1652055544088": {
    "address": "https://helpfulengineering.org/",
    "seconds": 4
  },
  "1652660522268": {
    "address": "https://helpfulengineering.org/",
    "seconds": 4
  },
  "1653265348320": {
    "address": "https://helpfulengineering.org/",
    "seconds": 4
  },
  "1653870252146": {
    "address": "https://helpfulengineering.org/",
    "seconds": 4
  },
  "1654474697819": {
    "address": "https://helpfulengineering.org/",
    "seconds": 4
  },
  "1655079769291": {
    "address": "https://helpfulengineering.org/",
    "seconds": 4
  },
  "1655684392660": {
    "address": "https://helpfulengineering.org/",
    "seconds": 4
  },
  "1656289407819": {
    "address": "https://helpfulengineering.org/",
    "seconds": 4
  },
  "1656894319818": {
    "address": "https://helpfulengineering.org/",
    "seconds": 5
  },
  "1657498836260": {
    "address": "https://helpfulengineering.org/",
    "seconds": 4
  },
  "1658103666915": {
    "address": "https://helpfulengineering.org/",
    "seconds": 4
  },
  "1658708534450": {
    "address": "https://helpfulengineering.org/",
    "seconds": 4
  },
  "1659313570803": {
    "address": "https://helpfulengineering.org/",
    "seconds": 4
  },
  "1659917976201": {
    "address": "https://helpfulengineering.org/",
    "seconds": 3
  },
  "1660522938218": {
    "address": "https://helpfulengineering.org/",
    "seconds": 4
  },
  "1661127816337": {
    "address": "https://helpfulengineering.org/",
    "seconds": 4
  },
  "1661732668292": {
    "address": "https://helpfulengineering.org/",
    "seconds": 4
  },
  "1662337619607": {
    "address": "https://helpfulengineering.org/",
    "seconds": 4
  },
  "1662942201454": {
    "address": "https://helpfulengineering.org/",
    "seconds": 4
  },
  "1663547120302": {
    "address": "https://helpfulengineering.org/",
    "seconds": 5
  },
  "1664152022048": {
    "address": "https://helpfulengineering.org/",
    "seconds": 5
  },
  "1664756876545": {
    "address": "https://helpfulengineering.org/",
    "seconds": 4
  },
  "1665361819740": {
    "address": "https://helpfulengineering.org/",
    "seconds": 4
  },
  "1665966741609": {
    "address": "https://helpfulengineering.org/",
    "seconds": 0
  },
  "1666571626201": {
    "address": "https://helpfulengineering.org/",
    "seconds": 4
  },
  "1667176085604": {
    "address": "https://helpfulengineering.org/",
    "seconds": 4
  },
  "1667780563599": {
    "address": "https://helpfulengineering.org/",
    "seconds": 5
  },
  "1668385331854": {
    "address": "https://helpfulengineering.org/",
    "seconds": 5
  },
  "1668990190560": {
    "address": "https://helpfulengineering.org/",
    "seconds": 4
  },
  "1669594794968": {
    "address": "https://helpfulengineering.org/",
    "seconds": 4
  },
  "1670199629032": {
    "address": "https://helpfulengineering.org/",
    "seconds": 5
  },
  "1670804486550": {
    "address": "https://helpfulengineering.org/",
    "seconds": 4
  },
  "1671409084586": {
    "address": "https://helpfulengineering.org/",
    "seconds": 4
  },
  "1672014013364": {
    "address": "https://helpfulengineering.org/",
    "seconds": 4
  },
  "1672618804647": {
    "address": "https://helpfulengineering.org/",
    "seconds": 5
  },
  "1673223637082": {
    "address": "https://helpfulengineering.org/",
    "seconds": 4
  },
  "1673828450026": {
    "address": "https://helpfulengineering.org/",
    "seconds": 5
  },
  "1674433194235": {
    "address": "https://helpfulengineering.org/",
    "seconds": 5
  },
  "1675037883788": {
    "address": "https://helpfulengineering.org/",
    "seconds": 4
  },
  "1675642817304": {
    "address": "https://helpfulengineering.org/",
    "seconds": 5
  },
  "1676247716173": {
    "address": "https://helpfulengineering.org/",
    "seconds": 4
  },
  "1676852611160": {
    "address": "https://helpfulengineering.org/",
    "seconds": 5
  },
  "1677457341321": {
    "address": "https://helpfulengineering.org/",
    "seconds": 4
  },
  "1678062136786": {
    "address": "https://helpfulengineering.org/",
    "seconds": 5
  },
  "1678666883467": {
    "address": "https://helpfulengineering.org/",
    "seconds": 5
  },
  "1679271724953": {
    "address": "https://helpfulengineering.org/",
    "seconds": 5
  },
  "1679876414727": {
    "address": "https://helpfulengineering.org/",
    "seconds": 5
  },
  "1680481165743": {
    "address": "https://helpfulengineering.org/",
    "seconds": 5
  },
  "1681085961455": {
    "address": "https://helpfulengineering.org/",
    "seconds": 5
  },
  "1681690751770": {
    "address": "https://helpfulengineering.org/",
    "seconds": 4
  },
  "1682295583008": {
    "address": "https://helpfulengineering.org/",
    "seconds": 4
  },
  "1682900453394": {
    "address": "https://helpfulengineering.org/",
    "seconds": 4
  },
  "1683505113879": {
    "address": "https://helpfulengineering.org/",
    "seconds": 4
  },
  "1684110016889": {
    "address": "https://helpfulengineering.org/",
    "seconds": 4
  },
  "1684714851139": {
    "address": "https://helpfulengineering.org/",
    "seconds": 4
  },
  "1685319625880": {
    "address": "https://helpfulengineering.org/",
    "seconds": 4
  },
  "1685924521385": {
    "address": "https://helpfulengineering.org/",
    "seconds": 4
  },
  "1686529389437": {
    "address": "https://helpfulengineering.org/",
    "seconds": 4
  },
  "1687134192304": {
    "address": "https://helpfulengineering.org/",
    "seconds": 4
  },
  "1687739106540": {
    "address": "https://helpfulengineering.org/",
    "seconds": 5
  },
  "1688343889285": {
    "address": "https://helpfulengineering.org/",
    "seconds": 5
  },
  "1688948715426": {
    "address": "https://helpfulengineering.org/",
    "seconds": 4
  },
  "1689553550450": {
    "address": "https://helpfulengineering.org/",
    "seconds": 5
  },
  "1690158132569": {
    "address": "https://helpfulengineering.org/",
    "seconds": 4
  },
  "1690762874872": {
    "address": "https://helpfulengineering.org/",
    "seconds": 4
  },
  "1691367770492": {
    "address": "https://helpfulengineering.org/",
    "seconds": 4
  },
  "1691972305995": {
    "address": "https://helpfulengineering.org/",
    "seconds": 5
  },
  "1692577086612": {
    "address": "https://helpfulengineering.org/",
    "seconds": 5
  },
  "1693181897002": {
    "address": "https://helpfulengineering.org/",
    "seconds": 4
  },
  "1693786721568": {
    "address": "https://helpfulengineering.org/",
    "seconds": 4
  },
  "1694391533080": {
    "address": "https://helpfulengineering.org/",
    "seconds": 4
  },
  "1694996330595": {
    "address": "https://helpfulengineering.org/",
    "seconds": 4
  },
  "1695601151270": {
    "address": "https://helpfulengineering.org/",
    "seconds": 4
  },
  "1696205950306": {
    "address": "https://helpfulengineering.org/",
    "seconds": 4
  },
  "1696810762114": {
    "address": "https://helpfulengineering.org/",
    "seconds": 5
  },
  "1697415590459": {
    "address": "https://helpfulengineering.org/",
    "seconds": 5
  },
  "1698625145036": {
    "address": "https://helpfulengineering.org/",
    "seconds": 4
  },
  "1699229975032": {
    "address": "https://helpfulengineering.org/",
    "seconds": 4
  },
  "1699834812724": {
    "address": "https://helpfulengineering.org/",
    "seconds": 5
  }
}
